.venv/bin/activate_this.py
.venv/lib/python3.7/site-packages/_virtualenv.py
.venv/lib/python3.7/site-packages/typing_extensions.py
.venv/lib/python3.7/site-packages/_yaml/__init__.py
.venv/lib/python3.7/site-packages/click/__init__.py
.venv/lib/python3.7/site-packages/click/_compat.py
.venv/lib/python3.7/site-packages/click/_termui_impl.py
.venv/lib/python3.7/site-packages/click/_textwrap.py
.venv/lib/python3.7/site-packages/click/_winconsole.py
.venv/lib/python3.7/site-packages/click/core.py
.venv/lib/python3.7/site-packages/click/decorators.py
.venv/lib/python3.7/site-packages/click/exceptions.py
.venv/lib/python3.7/site-packages/click/formatting.py
.venv/lib/python3.7/site-packages/click/globals.py
.venv/lib/python3.7/site-packages/click/parser.py
.venv/lib/python3.7/site-packages/click/shell_completion.py
.venv/lib/python3.7/site-packages/click/termui.py
.venv/lib/python3.7/site-packages/click/types.py
.venv/lib/python3.7/site-packages/click/utils.py
.venv/lib/python3.7/site-packages/greenlet/__init__.py
.venv/lib/python3.7/site-packages/greenlet/platform/__init__.py
.venv/lib/python3.7/site-packages/importlib_metadata/__init__.py
.venv/lib/python3.7/site-packages/importlib_metadata/_adapters.py
.venv/lib/python3.7/site-packages/importlib_metadata/_collections.py
.venv/lib/python3.7/site-packages/importlib_metadata/_compat.py
.venv/lib/python3.7/site-packages/importlib_metadata/_functools.py
.venv/lib/python3.7/site-packages/importlib_metadata/_itertools.py
.venv/lib/python3.7/site-packages/importlib_metadata/_meta.py
.venv/lib/python3.7/site-packages/importlib_metadata/_py39compat.py
.venv/lib/python3.7/site-packages/importlib_metadata/_text.py
.venv/lib/python3.7/site-packages/sqlalchemy/__init__.py
.venv/lib/python3.7/site-packages/sqlalchemy/events.py
.venv/lib/python3.7/site-packages/sqlalchemy/exc.py
.venv/lib/python3.7/site-packages/sqlalchemy/inspection.py
.venv/lib/python3.7/site-packages/sqlalchemy/log.py
lesscode_tool-0.0.38.dist-info/METADATA
lesscode_tool-0.0.38.dist-info/WHEEL
lesscode_tool-0.0.38.dist-info/entry_points.txt
lesscode_tool-0.0.38.dist-info/licenses/LICENSE
lesscode_tool-0.0.38.dist-info/RECORD
