Metadata-Version: 2.1
Name: lesscode-tool
Version: 0.0.38
Summary: 低代码生成工具
Author-email: navysummer <navysummer@yeah.net>
License: MIT License
License-File: LICENSE
Classifier: License :: OSI Approved :: MIT License
Classifier: Operating System :: OS Independent
Classifier: Programming Language :: Python :: 3
Requires-Python: >=3.7
Requires-Dist: click~=8.1.3
Requires-Dist: pyyaml>=6.0.1
Requires-Dist: sqlalchemy>=2.0.40
